ailabtools/__init__.py
ailabtools/ailab_multiprocessing.py
ailabtools/common.py
ailabtools/connection_pool_postgresql.py
ailabtools/extract_distinct_image.py
ailabtools/image_file_processer.py
ailabtools/statistic.py
ailabtools/zaco.py
ailabtools/zlogger.py
ailabtools/imgutils/__init__.py
ailabtools/imgutils/check_duplicate_image.py
ailabtools/imgutils/extract_distinct_image.py
ailabtools/imgutils/image_file_processer.py
ailabtools/keras/__init__.py
ailabtools/keras/callback.py
ailabtools/keras/callbacks.py
ailabtools/keras/classify_trainer.py
ailabtools/keras/model_optimize.py
ailabtools/keras/pairgenerator.py
ailabtools/keras/tflite_model.py
ailabtools/keras/utils.py
ailabtools/mass_detector/__init__.py
ailabtools/mass_detector/mass_detector.py
ailabtools/utils/__init__.py
ailabtools/utils/common_import.py
ailabtools/utils/network.py
ailabtools/utils/path.py
ailabtools/utils/profiler.py
ailabtools/utils/vis.py
ailabtools-0.0.64.dist-info/LICENSE
ailabtools-0.0.64.dist-info/METADATA
ailabtools-0.0.64.dist-info/WHEEL
ailabtools-0.0.64.dist-info/top_level.txt
ailabtools-0.0.64.dist-info/RECORD
