Metadata-Version: 2.1
Name: ailabtools
Version: 0.0.64
Summary: Common tools for Zalo AILab
Home-page: https://lab.zalo.ai
Author: Zalo AILab
Classifier: Programming Language :: Python :: 3
Classifier: License :: OSI Approved :: MIT License
Classifier: Operating System :: OS Independent
License-File: LICENSE
